netSplit.py
pynetsplit-3.10.0.data/data/VERSION
pynetsplit-3.10.0.dist-info/licenses/COPYING.md
pynetsplit-3.10.0.dist-info/METADATA
pynetsplit-3.10.0.dist-info/WHEEL
pynetsplit-3.10.0.dist-info/top_level.txt
pynetsplit-3.10.0.dist-info/RECORD
