Metadata-Version: 2.4
Name: PyNetSplit
Version: 3.10.0
Summary: NetSplit
Home-page: https://github.com/Omena0/NetSplit
Author: Omena0
License: PolyForm Noncommercial 1.0.0
Classifier: Programming Language :: Python :: 3
Classifier: Programming Language :: Python :: 3.13
Classifier: License :: Other/Proprietary License
Classifier: Operating System :: OS Independent
Requires-Python: >=3.8
License-File: COPYING.md
Dynamic: description
Dynamic: description-content-type
Dynamic: license-file
Dynamic: summary
